minecraft_launch/__init__.py
minecraft_launch/launch/__init__.py
minecraft_launch/launch/java_minecraft_launcher.py
minecraft_launch/modules/__init__.py
minecraft_launch/modules/arguments_builders/__init__.py
minecraft_launch/modules/arguments_builders/java_minecraft_arguments_builder.py
minecraft_launch/modules/enum/__init__.py
minecraft_launch/modules/enum/account_type.py
minecraft_launch/modules/enum/launch_state.py
minecraft_launch/modules/enum/mod_loader_type.py
minecraft_launch/modules/installer/__init__.py
minecraft_launch/modules/installer/game_core_installer.py
minecraft_launch/modules/installer/resource_installer.py
minecraft_launch/modules/interface/__init__.py
minecraft_launch/modules/interface/installer_base.py
minecraft_launch/modules/interface/iresource.py
minecraft_launch/modules/interface/launcher_base.py
minecraft_launch/modules/models/__init__.py
minecraft_launch/modules/models/auth/__init__.py
minecraft_launch/modules/models/auth/account.py
minecraft_launch/modules/models/auth/offline_account.py
minecraft_launch/modules/models/download/__init__.py
minecraft_launch/modules/models/download/api_manager.py
minecraft_launch/modules/models/download/download_api.py
minecraft_launch/modules/models/download/download_request.py
minecraft_launch/modules/models/download/file_resource.py
minecraft_launch/modules/models/download/library_resource.py
minecraft_launch/modules/models/install/__init__.py
minecraft_launch/modules/models/install/game_core_entity.py
minecraft_launch/modules/models/install/game_cores_entity.py
minecraft_launch/modules/models/install/installer_response.py
minecraft_launch/modules/models/install/installer_response_base.py
minecraft_launch/modules/models/launch/__init__.py
minecraft_launch/modules/models/launch/game_core.py
minecraft_launch/modules/models/launch/game_window_config.py
minecraft_launch/modules/models/launch/jvm_config.py
minecraft_launch/modules/models/launch/launch_config.py
minecraft_launch_p-0.1.2.dist-info/METADATA
minecraft_launch_p-0.1.2.dist-info/WHEEL
minecraft_launch_p-0.1.2.dist-info/top_level.txt
minecraft_launch_p-0.1.2.dist-info/RECORD
