Metadata-Version: 2.1
Name: minecraft-launch-p
Version: 0.1.2
Summary: Python edition of MinecraftLaunch, a .Net Minecraft launcher core
Home-page: https://github.com/Blessing-Studio/minecraft-launch-p
Author: JustRainy
Author-email: 1831719639@qq.com
Keywords: Minecraft launcher core
Classifier: Programming Language :: Python :: 3
Classifier: License :: OSI Approved :: MIT License
Classifier: Operating System :: OS Independent
Requires-Python: >=3.11
Requires-Dist: aiofiles >=23.2.1
Requires-Dist: urllib3 >=2.0.4
